src/__init__.py
src/__version__.py
src/test.py
dxh_test_package-1.1.1.dist-info/LICENSE
dxh_test_package-1.1.1.dist-info/METADATA
dxh_test_package-1.1.1.dist-info/WHEEL
dxh_test_package-1.1.1.dist-info/top_level.txt
dxh_test_package-1.1.1.dist-info/RECORD
