Metadata-Version: 2.1
Name: dxh-test-package
Version: 1.1.1
Summary: This package is utilized for testing purposes in the learning process.
Home-page: https://github.com/git-mehedi/dxh_test_package
Author: Mehedi Hasan
License: MIT
Project-URL: Source, https://github.com/git-mehedi/dxh_test_package
Keywords: test
Classifier: Intended Audience :: Developers
Classifier: License :: OSI Approved :: MIT License
Classifier: Natural Language :: English
Classifier: Operating System :: OS Independent
Classifier: Programming Language :: Python :: 3
Classifier: Programming Language :: Python :: 3.6
Classifier: Programming Language :: Python :: 3.7
Classifier: Programming Language :: Python :: 3.8
Classifier: Topic :: Internet :: WWW/HTTP
Classifier: Topic :: Scientific/Engineering :: Information Analysis
Requires-Python: >=3.6
License-File: LICENSE
Requires-Dist: twine
Requires-Dist: setuptools
Requires-Dist: pytest <9,>=2.8.0
Requires-Dist: pytest-cov
Requires-Dist: pytest-httpbin ==2.0.0
Requires-Dist: httpbin ~=0.10.0
Requires-Dist: trustme
Requires-Dist: wheel
